xmnlp/__init__.py
xmnlp/base_model.py
xmnlp/dict.big.txt
xmnlp/module.py
xmnlp/stopword.txt
xmnlp/trainer.py
xmnlp/checker/__init__.py
xmnlp/checker/checker.py
xmnlp/config/__init__.py
xmnlp/config/path.py
xmnlp/lexical/__init__.py
xmnlp/lexical/lexical_model.py
xmnlp/lexical/tokenization.py
xmnlp/pinyin/__init__.py
xmnlp/pinyin/pinyin.pickle
xmnlp/pinyin/pinyin.py
xmnlp/radical/__init__.py
xmnlp/radical/radical.pickle
xmnlp/radical/radical.py
xmnlp/sentiment/__init__.py
xmnlp/sentiment/sentiment_model.py
xmnlp/summary/__init__.py
xmnlp/summary/textrank.py
xmnlp/sv/__init__.py
xmnlp/sv/model.py
xmnlp/utils/__init__.py
xmnlp/utils/bm25.py
xmnlp/utils/trie.py
xmnlp-0.5.3.dist-info/LICENSE
xmnlp-0.5.3.dist-info/METADATA
xmnlp-0.5.3.dist-info/WHEEL
xmnlp-0.5.3.dist-info/top_level.txt
xmnlp-0.5.3.dist-info/RECORD
