Metadata-Version: 2.1
Name: xmnlp
Version: 0.5.3
Summary: A Lightweight Chinese Natural Language Processing Toolkit
Home-page: https://github.com/SeanLee97/xmnlp
Author: sean lee
Author-email: xmlee97@gmail.com
License: Apache 2.0 License
Keywords: chinese segmentation,chinese postager,chinese spell check,pinyin,chinese radical
Platform: all
Classifier: Intended Audience :: Developers
Classifier: Operating System :: OS Independent
Classifier: License :: OSI Approved :: MIT License
Classifier: Programming Language :: Python
Classifier: Programming Language :: Python :: 3
Classifier: Programming Language :: Python :: 3.6
Classifier: Programming Language :: Python :: 3.7
Classifier: Programming Language :: Python :: 3.8
Classifier: Topic :: Text Processing
Classifier: Topic :: Text Processing :: Indexing
Classifier: Topic :: Text Processing :: Linguistic
Requires-Dist: tokenizers
Requires-Dist: scikit-learn
Requires-Dist: numpy
Requires-Dist: onnxruntime (==1.9.0)
